[{"family":"MaterialIcons","fonts":[{"asset":"fonts/MaterialIcons-Regular.otf"}]},{"family":"GeneralSans","fonts":[{"weight":200,"asset":"assets/fonts/generalsansextralight.ttf"},{"weight":300,"asset":"assets/fonts/generalsanslight.ttf"},{"weight":400,"asset":"assets/fonts/generalsansregular.ttf"},{"weight":500,"asset":"assets/fonts/generalsansmedium.ttf"},{"weight":600,"asset":"assets/fonts/generalsanssemibold.ttf"},{"weight":700,"asset":"assets/fonts/generalsansbold.ttf"}]},{"family":"Inter","fonts":[{"weight":100,"asset":"assets/fonts/interthin.ttf"},{"weight":200,"asset":"assets/fonts/interextralight.ttf"},{"weight":300,"asset":"assets/fonts/interlight.ttf"},{"weight":400,"asset":"assets/fonts/interregular.ttf"},{"weight":500,"asset":"assets/fonts/intermedium.ttf"},{"weight":600,"asset":"assets/fonts/intersemibold.ttf"},{"weight":700,"asset":"assets/fonts/interbold.ttf"},{"weight":800,"asset":"assets/fonts/interextrabold.ttf"},{"weight":900,"asset":"assets/fonts/interblack.ttf"}]},{"family":"packages/ionicons/Ionicons","fonts":[{"asset":"packages/ionicons/assets/fonts/Ionicons.ttf"}]}]